filenuke/__init__.py
filenuke/nuke.py
filenuke-0.0.0.dist-info/LICENSE
filenuke-0.0.0.dist-info/METADATA
filenuke-0.0.0.dist-info/WHEEL
filenuke-0.0.0.dist-info/top_level.txt
filenuke-0.0.0.dist-info/RECORD
