Metadata-Version: 2.1
Name: filenuke
Version: 0.0.0
Summary: Securely erase files or directories as much as possible from userspace
Home-page: https://chaoswebs.net/
Author: Kevin Froman
Author-email: beardog@mailbox.org
License: UNKNOWN
Platform: UNKNOWN
Classifier: Programming Language :: Python :: 3
Classifier: License :: OSI Approved :: GNU General Public License v3 (GPLv3)
Classifier: Operating System :: OS Independent
Requires-Python: >=3.6
